collective.portletmetadata-2.0.0-py3.11-nspkg.pth
collective/portletmetadata/__init__.py
collective/portletmetadata/column.pt
collective/portletmetadata/configure.zcml
collective/portletmetadata/controlpanel.py
collective/portletmetadata/interfaces.py
collective/portletmetadata/manager.py
collective/portletmetadata/messagefactory.py
collective/portletmetadata/metadata.py
collective/portletmetadata/patches.py
collective/portletmetadata/testing.py
collective/portletmetadata/vocabularies.py
collective/portletmetadata/overrides/Products.ContentWellPortlets.browser.templates.renderer.pt
collective/portletmetadata/overrides-5/plone.app.portlets.browser.templates.edit-manager-macros.pt
collective/portletmetadata/overrides-6/plone.app.portlets.browser.templates.edit-manager-macros.pt
collective/portletmetadata/profiles/default/browserlayer.xml
collective/portletmetadata/profiles/default/controlpanel.xml
collective/portletmetadata/profiles/default/metadata.xml
collective/portletmetadata/profiles/default/registry.xml
collective/portletmetadata/profiles/default/rolemap.xml
collective/portletmetadata/profiles/uninstall/browserlayer.xml
collective/portletmetadata/profiles/uninstall/controlpanel.xml
collective/portletmetadata/profiles/uninstall/registry.xml
collective/portletmetadata/tests/__init__.py
collective/portletmetadata/tests/configure.zcml
collective/portletmetadata/tests/test_functional.py
collective/portletmetadata/tests/profile/metadata.xml
collective/portletmetadata/tests/profile/portlets.xml
collective.portletmetadata-2.0.0.dist-info/METADATA
collective.portletmetadata-2.0.0.dist-info/WHEEL
collective.portletmetadata-2.0.0.dist-info/entry_points.txt
collective.portletmetadata-2.0.0.dist-info/namespace_packages.txt
collective.portletmetadata-2.0.0.dist-info/top_level.txt
collective.portletmetadata-2.0.0.dist-info/RECORD
