Metadata-Version: 2.1
Name: collective.portletmetadata
Version: 2.0.0
Summary: Adds metadata functionality to portlets
Home-page: http://github.com/collective/collective.portletmetadata
Author: Bo Simonsen
Author-email: bo@headnet.dk
License: GPL
Keywords: portlets metadata class
Classifier: Development Status :: 5 - Production/Stable
Classifier: Framework :: Plone
Classifier: Framework :: Plone :: 6.0
Classifier: License :: OSI Approved :: GNU General Public License (GPL)
Classifier: Programming Language :: Python
Classifier: Programming Language :: Python :: 3.8
Classifier: Programming Language :: Python :: 3.9
Classifier: Programming Language :: Python :: 3.10
Classifier: Programming Language :: Python :: 3.11
Requires-Python: >=3.8
Requires-Dist: collective.monkeypatcher
Requires-Dist: plone.app.portlets
Requires-Dist: plone.app.registry
Requires-Dist: plone.autoform
Requires-Dist: plone.base
Requires-Dist: plone.memoize
Requires-Dist: plone.portlets
Requires-Dist: Products.GenericSetup
Requires-Dist: setuptools
Requires-Dist: z3c.form
Requires-Dist: z3c.jbot
Requires-Dist: z3c.unconfigure (>=1.0.1)
Provides-Extra: test
Requires-Dist: plone.testing ; extra == 'test'
Requires-Dist: plone.app.testing ; extra == 'test'
